{
  "project": "AI魔法棒",
  "date": "2026-05-17",
  "quantity": "5000套",
  "total_quantity": 5000,
  "batch_quantity": 5000,
  "versions": [
    "经济版",
    "标准版"
  ],
  "selected_version": "经济版",
  "ai_suggestion": "经济版适合云端AI方案快速验证，标准版16MB Flash可缓存轻量端侧模型。两个版本共享同一ESP32-S3平台，降低开发维护成本。建议优先打样经济版验证功能，再升级标准版。",
  "risk_tags": [
    {
      "tag": "ESP32-S3 GPIO紧张",
      "level": "mid",
      "desc": "10个外设子系统占用约37个GPIO，余量仅8个，后续扩展需谨慎"
    },
    {
      "tag": "4G模块成本占比高",
      "level": "mid",
      "desc": "Air780E约¥46，占总BOM 35%以上，可评估合宙裸模块进一步压价"
    },
    {
      "tag": "NFC芯片PN532较贵",
      "level": "low",
      "desc": "商城价¥39.96偏高，大批量可考虑NT3H2111被动方案降为¥2-3"
    },
    {
      "tag": "续航约3小时",
      "level": "mid",
      "desc": "1200mAh电池在持续使用场景下续航有限，可考虑增大电池或降低功耗"
    }
  ],
  "items": [
    {
      "id": 1,
      "category": "MCU",
      "is_variant": true,
      "func_impact": "主控性能",
      "exp_impact": "识别速度",
      "user_value": "高",
      "cost_tier": "high",
      "note": "ESP32-S3内置WiFi+BLE省去独立无线模块，DVP摄像头接口成熟",
      "variants": [
        {
          "version": "经济版",
          "brand": "乐鑫",
          "package": "Module",
          "part_number": "ESP32-S3-WROOM-1-N8R8",
          "description": "240MHz 双核, WiFi+BLE5, 8MB Flash, 8MB PSRAM, DVP Camera",
          "price_mall": 20.73,
          "mall_source": "华秋商城+立创商城（双源验证）",
          "mall_url": "https://www.hqchip.com/search.html?keyword=ESP32-S3-WROOM-1-N8R8",
          "price_ai": 0.263,
          "ai_source": "博查",
          "found": true,
          "price_unit": 20.73,
          "cost_ratio": 12.0
        },
        {
          "version": "标准版",
          "brand": "乐鑫",
          "package": "Module",
          "part_number": "ESP32-S3-WROOM-1-N16R8",
          "description": "240MHz 双核, WiFi+BLE5, 16MB Flash, 8MB PSRAM, DVP Camera",
          "price_mall": 19.79,
          "mall_source": "华秋商城+立创商城（双源验证）",
          "mall_url": "https://www.hqchip.com/search.html?keyword=ESP32-S3-WROOM-1-N16R8",
          "price_ai": 20.0,
          "ai_source": "博查",
          "found": true,
          "price_unit": 19.79,
          "cost_ratio": 11.5
        }
      ]
    },
    {
      "id": 2,
      "category": "存储-Flash",
      "is_variant": true,
      "func_impact": "模型存储",
      "exp_impact": "离线能力",
      "user_value": "中",
      "cost_tier": "low",
      "note": "WROOM模组内置Flash，无需外挂",
      "variants": [
        {
          "version": "经济版",
          "brand": "-",
          "package": "-",
          "part_number": "MCU 内置",
          "description": "8MB Flash (WROOM模组内)",
          "price_mall": null,
          "mall_source": "",
          "mall_url": "",
          "price_ai": 0,
          "ai_source": "经验预估",
          "found": false,
          "price_unit": 0,
          "cost_ratio": 0.0
        },
        {
          "version": "标准版",
          "brand": "-",
          "package": "-",
          "part_number": "MCU 内置",
          "description": "16MB Flash (WROOM模组内)",
          "price_mall": null,
          "mall_source": "",
          "mall_url": "",
          "price_ai": 0,
          "ai_source": "经验预估",
          "found": false,
          "price_unit": 0,
          "cost_ratio": 0.0
        }
      ]
    },
    {
      "id": 3,
      "category": "存储-内存",
      "is_variant": true,
      "func_impact": "运行内存",
      "exp_impact": "缓冲性能",
      "user_value": "中",
      "cost_tier": "low",
      "note": "WROOM模组内置PSRAM，无需外挂",
      "variants": [
        {
          "version": "经济版",
          "brand": "-",
          "package": "-",
          "part_number": "MCU 内置",
          "description": "8MB PSRAM (WROOM模组内)",
          "price_mall": null,
          "mall_source": "",
          "mall_url": "",
          "price_ai": 0,
          "ai_source": "经验预估",
          "found": false,
          "price_unit": 0,
          "cost_ratio": 0.0
        },
        {
          "version": "标准版",
          "brand": "-",
          "package": "-",
          "part_number": "MCU 内置",
          "description": "8MB PSRAM (WROOM模组内)",
          "price_mall": null,
          "mall_source": "",
          "mall_url": "",
          "price_ai": 0,
          "ai_source": "经验预估",
          "found": false,
          "price_unit": 0,
          "cost_ratio": 0.0
        }
      ]
    },
    {
      "id": 4,
      "category": "摄像头",
      "is_variant": true,
      "func_impact": "识别精度",
      "exp_impact": "画质提升",
      "user_value": "高",
      "cost_tier": "high",
      "note": "经济版VGA够云端识别，标准版2MP准确率更高",
      "variants": [
        {
          "version": "经济版",
          "brand": "GalaxyCore",
          "package": "DVP模组",
          "part_number": "GC032A 模组",
          "description": "0.3MP VGA, DVP 8-bit, 含镜头+FPC",
          "price_mall": 0.83,
          "mall_source": "立创商城",
          "mall_url": "https://so.szlcsc.com/global.html?k=GC032A",
          "price_ai": 4.3,
          "ai_source": "博查",
          "found": true,
          "price_unit": 0.83,
          "cost_ratio": 0.5
        },
        {
          "version": "标准版",
          "brand": "GalaxyCore",
          "package": "DVP模组",
          "part_number": "GC2145 模组",
          "description": "2MP, DVP 8-bit, 含镜头+FPC",
          "price_mall": 0.83,
          "mall_source": "立创商城",
          "mall_url": "https://so.szlcsc.com/global.html?k=GC2145",
          "price_ai": 2.9,
          "ai_source": "博查",
          "found": true,
          "price_unit": 0.83,
          "cost_ratio": 0.5
        }
      ]
    },
    {
      "id": 5,
      "category": "显示",
      "is_variant": true,
      "func_impact": "信息展示",
      "exp_impact": "显示效果",
      "user_value": "中",
      "cost_tier": "mid",
      "note": "经济版128x160够显示文字结果，标准版240x240可展示简单UI",
      "variants": [
        {
          "version": "经济版",
          "brand": "合力泰",
          "package": "SPI模组",
          "part_number": "1.3寸 ST7735S 模组",
          "description": "128x160, SPI, 含FPC连接器",
          "price_mall": 6.38,
          "mall_source": "立创商城",
          "mall_url": "https://so.szlcsc.com/global.html?k=ST7735S+1.3",
          "price_ai": 0.81,
          "ai_source": "博查",
          "found": true,
          "price_unit": 6.38,
          "cost_ratio": 3.7
        },
        {
          "version": "标准版",
          "brand": "合力泰",
          "package": "SPI模组",
          "part_number": "1.54寸 ST7789V 模组",
          "description": "240x240, SPI, 含FPC连接器",
          "price_mall": 31.06,
          "mall_source": "立创商城",
          "mall_url": "https://so.szlcsc.com/global.html?k=ST7789V+1.54",
          "price_ai": 1.3,
          "ai_source": "博查",
          "found": true,
          "price_unit": 31.06,
          "cost_ratio": 18.0
        }
      ]
    },
    {
      "id": 6,
      "category": "4G_5G",
      "is_variant": false,
      "brand": "合宙",
      "package": "LCC",
      "part_number": "Air780E",
      "description": "Cat.1 4G模组, UART接口, 支持VoLTE",
      "price_mall": 46.25,
      "mall_source": "立创商城",
      "mall_url": "https://so.szlcsc.com/global.html?k=Air780E",
      "price_ai": 4.0,
      "ai_source": "博查",
      "found": true,
      "func_impact": "移动联网",
      "exp_impact": "随时在线",
      "user_value": "高",
      "cost_tier": "high",
      "note": "国产Cat.1最便宜方案, UART接口简单, 大批量可进一步压价",
      "price_unit": 46.25,
      "cost_ratio": 26.8
    },
    {
      "id": 7,
      "category": "GPS",
      "is_variant": false,
      "brand": "中科微",
      "package": "模组",
      "part_number": "ATGM336H 模组",
      "description": "GPS/北斗双模GNSS模组, UART, 含陶瓷天线",
      "price_mall": 11.28,
      "mall_source": "立创商城",
      "mall_url": "https://so.szlcsc.com/global.html?k=ATGM336H",
      "price_ai": 18.0,
      "ai_source": "博查",
      "found": true,
      "func_impact": "位置服务",
      "exp_impact": "定位精度",
      "user_value": "中",
      "cost_tier": "mid",
      "note": "国产最便宜GNSS方案, 支持北斗+GPS双模",
      "price_unit": 11.28,
      "cost_ratio": 6.5
    },
    {
      "id": 8,
      "category": "NFC",
      "is_variant": false,
      "brand": "NXP",
      "package": "QFN-40",
      "part_number": "PN532",
      "description": "主动读写NFC标签, SPI接口, 支持13.56MHz",
      "price_mall": 39.96,
      "mall_source": "华秋商城+立创商城（双源验证）",
      "mall_url": "https://www.hqchip.com/search.html?keyword=PN532",
      "price_ai": 12.3,
      "ai_source": "博查",
      "found": true,
      "func_impact": "近场交互",
      "exp_impact": "操作便捷",
      "user_value": "中",
      "cost_tier": "mid",
      "note": "支持主动扫描NFC标签, 适合魔法棒场景; 大批量可考虑NT3H2111被动方案降本",
      "price_unit": 39.96,
      "cost_ratio": 23.1
    },
    {
      "id": 9,
      "category": "IMU",
      "is_variant": false,
      "brand": "TDK",
      "package": "QFN-24",
      "part_number": "MPU-6050",
      "description": "6轴(3轴加速度+3轴陀螺仪), I2C接口",
      "price_mall": 39.0,
      "mall_source": "华秋商城+立创商城（双源验证）",
      "mall_url": "https://www.hqchip.com/search.html?keyword=MPU-6050",
      "price_ai": 0.18,
      "ai_source": "博查",
      "found": true,
      "func_impact": "运动感知",
      "exp_impact": "体感交互",
      "user_value": "中",
      "cost_tier": "mid",
      "note": "最成熟6轴IMU方案, 商城价偏高(含进口税), 大批量可换国产ICP-10111或BMI270",
      "price_unit": 39.0,
      "cost_ratio": 22.6
    },
    {
      "id": 10,
      "category": "麦克风",
      "is_variant": false,
      "brand": "敏芯微",
      "package": "LGA",
      "part_number": "MSM261S4030H0R",
      "description": "MEMS数字麦克风, I2S输出, 底部进声",
      "price_mall": 7.98,
      "mall_source": "华秋商城",
      "mall_url": "https://www.hqchip.com/search.html?keyword=MSM261S4030H0R",
      "price_ai": 1.8,
      "ai_source": "博查",
      "found": true,
      "func_impact": "语音输入",
      "exp_impact": "拾音质量",
      "user_value": "低",
      "cost_tier": "low",
      "note": "国产MEMS数字麦, I2S直连ESP32-S3",
      "price_unit": 7.98,
      "cost_ratio": 4.6
    },
    {
      "id": 11,
      "category": "扬声器",
      "is_variant": false,
      "brand": "国光",
      "package": "8mm",
      "part_number": "8mm 0.5W 全频扬声器",
      "description": "0.5W 8ohm 全频扬声器, 适用于细长棒体",
      "price_mall": null,
      "mall_source": "",
      "mall_url": "",
      "price_ai": 1.5,
      "ai_source": "经验预估",
      "found": true,
      "func_impact": "语音输出",
      "exp_impact": "音质",
      "user_value": "低",
      "cost_tier": "low",
      "note": "小型扬声器, 候选品牌: 瑞声/歌尔/国光",
      "price_unit": 1.5,
      "cost_ratio": 0.9
    },
    {
      "id": 12,
      "category": "音频功放",
      "is_variant": false,
      "brand": "纳芯微",
      "package": "SSOT-23-5",
      "part_number": "NS4150",
      "description": "Class-D 3W 音频功放, I2S/模拟输入",
      "price_mall": 0.48,
      "mall_source": "华秋商城+立创商城（双源验证）",
      "mall_url": "https://www.hqchip.com/search.html?keyword=NS4150",
      "price_ai": 0.07,
      "ai_source": "博查",
      "found": true,
      "func_impact": "音频驱动",
      "exp_impact": "音量",
      "user_value": "低",
      "cost_tier": "low",
      "note": "国产Class-D功放, 超低成本",
      "price_unit": 0.48,
      "cost_ratio": 0.3
    },
    {
      "id": 13,
      "category": "电源",
      "is_variant": false,
      "brand": "英集芯",
      "package": "ESOP-8",
      "part_number": "IP2312",
      "description": "开关式充电管理IC, 2A, 支持Type-C CC",
      "price_mall": 0.92,
      "mall_source": "华秋商城+立创商城（双源验证）",
      "mall_url": "https://www.hqchip.com/search.html?keyword=IP2312",
      "price_ai": 0.12,
      "ai_source": "博查",
      "found": true,
      "func_impact": "充电效率",
      "exp_impact": "充电速度",
      "user_value": "中",
      "cost_tier": "low",
      "note": "开关式效率高发热小, 2A快充",
      "price_unit": 0.92,
      "cost_ratio": 0.5
    },
    {
      "id": 14,
      "category": "电源",
      "is_variant": false,
      "brand": "矽力杰",
      "package": "SOT-23-5",
      "part_number": "SY8089",
      "description": "Buck DC-DC, 3.3V输出, 1.5A",
      "price_mall": 0.35,
      "mall_source": "华秋商城+立创商城（双源验证）",
      "mall_url": "https://www.hqchip.com/search.html?keyword=SY8089",
      "price_ai": 0.28,
      "ai_source": "博查",
      "found": true,
      "func_impact": "供电稳定",
      "exp_impact": "可靠性",
      "user_value": "中",
      "cost_tier": "low",
      "note": "1.5A满足ESP32-S3 WiFi TX峰值功耗",
      "price_unit": 0.35,
      "cost_ratio": 0.2
    },
    {
      "id": 15,
      "category": "电池",
      "is_variant": false,
      "brand": "鹏辉能源",
      "package": "圆柱",
      "part_number": "103450 1200mAh",
      "description": "3.7V 1200mAh 圆柱锂电池, 10x34mm",
      "price_mall": 2.42,
      "mall_source": "立创商城",
      "mall_url": "https://so.szlcsc.com/global.html?k=103450+1200mAh",
      "price_ai": 3.95,
      "ai_source": "博查",
      "found": true,
      "func_impact": "续航时间",
      "exp_impact": "使用时长",
      "user_value": "高",
      "cost_tier": "mid",
      "note": "圆柱形适合棒体, 1200mAh约3h连续使用续航",
      "price_unit": 2.42,
      "cost_ratio": 1.4
    },
    {
      "id": 16,
      "category": "晶振",
      "is_variant": false,
      "brand": "-",
      "package": "-",
      "part_number": "MCU 内置",
      "description": "ESP32-S3-WROOM模组内置40MHz晶振",
      "price_mall": null,
      "mall_source": "",
      "mall_url": "",
      "price_ai": 0,
      "ai_source": "经验预估",
      "found": false,
      "func_impact": "时钟基准",
      "exp_impact": "稳定性",
      "user_value": "低",
      "cost_tier": "low",
      "note": "ESP32-S3-WROOM模组内置, 无需外挂",
      "price_unit": 0,
      "cost_ratio": 0.0
    },
    {
      "id": 17,
      "category": "按键",
      "is_variant": false,
      "brand": "国光",
      "package": "SMD",
      "part_number": "4x4 轻触开关",
      "description": "电源键 + 拍照/动作键, x2",
      "price_mall": null,
      "mall_source": "",
      "mall_url": "",
      "price_ai": 0.2,
      "ai_source": "经验预估",
      "found": true,
      "func_impact": "用户交互",
      "exp_impact": "操作体验",
      "user_value": "中",
      "cost_tier": "low",
      "note": "最小化交互: 电源 + 拍照",
      "price_unit": 0.2,
      "cost_ratio": 0.1
    },
    {
      "id": 18,
      "category": "LED",
      "is_variant": false,
      "brand": "混用",
      "package": "0603",
      "part_number": "0603 SMD LED",
      "description": "红绿双色电源LED + 蓝色状态LED, x2",
      "price_mall": null,
      "mall_source": "",
      "mall_url": "",
      "price_ai": 0.06,
      "ai_source": "经验预估",
      "found": true,
      "func_impact": "状态指示",
      "exp_impact": "可感知性",
      "user_value": "低",
      "cost_tier": "low",
      "note": "电源指示 + 识别状态指示",
      "price_unit": 0.06,
      "cost_ratio": 0.0
    },
    {
      "id": 19,
      "category": "阻容感",
      "is_variant": false,
      "brand": "YAGEO",
      "package": "0402",
      "part_number": "0402 通用料",
      "description": "去耦100nF, 上拉4.7K/10K, 滤波22uF等, 约55颗",
      "price_mall": null,
      "mall_source": "",
      "mall_url": "",
      "price_ai": 1.5,
      "ai_source": "经验预估",
      "found": true,
      "func_impact": "电路稳定",
      "exp_impact": "可靠性",
      "user_value": "低",
      "cost_tier": "low",
      "note": "0402封装适合5000+量产, 候选: YAGEO/MURATA/国巨",
      "price_unit": 1.5,
      "cost_ratio": 0.9
    },
    {
      "id": 20,
      "category": "连接器",
      "is_variant": false,
      "brand": "嘉立创",
      "package": "各",
      "part_number": "USB-C + SIM + FPC + Battery",
      "description": "Type-C 16P + Nano SIM + FPC 0.5mm x2 + PH 2P电池座",
      "price_mall": null,
      "mall_source": "",
      "mall_url": "",
      "price_ai": 3.0,
      "ai_source": "经验预估",
      "found": true,
      "func_impact": "物理连接",
      "exp_impact": "可维护性",
      "user_value": "低",
      "cost_tier": "low",
      "note": "充电/通信/模组连接, 候选: 嘉立创/立讯/同泰电子",
      "price_unit": 3.0,
      "cost_ratio": 1.7
    },
    {
      "id": 21,
      "category": "天线",
      "is_variant": false,
      "brand": "嘉立创",
      "package": "IPEX",
      "part_number": "IPEX 4G 天线",
      "description": "IPEX接口4G全频段天线, WiFi/BLE模组内置PCB天线",
      "price_mall": null,
      "mall_source": "",
      "mall_url": "",
      "price_ai": 1.5,
      "ai_source": "经验预估",
      "found": true,
      "func_impact": "信号质量",
      "exp_impact": "通信稳定性",
      "user_value": "中",
      "cost_tier": "low",
      "note": "WiFi/BLE天线在ESP32-S3-WROOM内置, 仅需外接4G天线",
      "price_unit": 1.5,
      "cost_ratio": 0.9
    },
    {
      "id": 22,
      "category": "保护",
      "is_variant": false,
      "brand": "混用",
      "package": "0402/SOT",
      "part_number": "SRV05-4 + 自恢复保险丝",
      "description": "USB-C ESD防护 + 500mA自恢复保险丝",
      "price_mall": null,
      "mall_source": "",
      "mall_url": "",
      "price_ai": 0.5,
      "ai_source": "经验预估",
      "found": true,
      "func_impact": "安全防护",
      "exp_impact": "耐用性",
      "user_value": "低",
      "cost_tier": "low",
      "note": "电源输入过流保护 + USB ESD防护",
      "price_unit": 0.5,
      "cost_ratio": 0.3
    },
    {
      "id": 23,
      "category": "PCB",
      "is_variant": false,
      "brand": "嘉立创",
      "package": "4层",
      "part_number": "4层板 30x120mm",
      "description": "4层PCB 30x120mm 含SMT贴片, 5000套",
      "price_mall": null,
      "mall_source": "",
      "mall_url": "",
      "price_ai": 10.8,
      "ai_source": "经验预估",
      "found": true,
      "func_impact": "制造基础",
      "exp_impact": "信号完整性",
      "user_value": "中",
      "cost_tier": "mid",
      "note": "细长棒体PCB, 4层保证高速信号完整性, 计算: 12 x 1.0 x 0.9",
      "price_unit": 10.8,
      "cost_ratio": 6.3
    },
    {
      "id": 24,
      "category": "结构件",
      "is_variant": false,
      "brand": "定制",
      "package": "-",
      "part_number": "ABS 注塑外壳",
      "description": "魔法棒形ABS注塑外壳, 含按键窗口/镜头窗/屏幕窗",
      "price_mall": null,
      "mall_source": "",
      "mall_url": "",
      "price_ai": 5.0,
      "ai_source": "经验预估",
      "found": true,
      "func_impact": "外观品质",
      "exp_impact": "用户体验",
      "user_value": "中",
      "cost_tier": "mid",
      "note": "定制注塑, 5000套可摊薄模具费",
      "price_unit": 5.0,
      "cost_ratio": 2.9
    }
  ]
}